{
  "timestamp": "2026-02-16T17:42:37.451Z",
  "naturalLanguageQuery": "list all cloud security controls",
  "generatedSQL": "SELECT \"short\", \"long\"\nFROM \"allTrustControls\"\nWHERE \"category\" ILIKE 'Cloud Security';",
  "expectedSQL": "SELECT * FROM \"allTrustControls\" WHERE \"category\" = 'Cloud Security';",
  "resultsCount": 5,
  "expectedCount": ">=5",
  "passed": true,
  "score": 4.2,
  "explanation": "✓ Returns 5 relevant results",
  "source": "ai",
  "executionTime": "5271ms",
  "sqlModel": "arctic-text2sql",
  "judgeModel": "phi4-reasoning"
}